swarm_models/__init__.py
swarm_models/ai_suite_wrapper.py
swarm_models/base_llm.py
swarm_models/base_multimodal_model.py
swarm_models/base_tts.py
swarm_models/base_ttv.py
swarm_models/cog_vlm.py
swarm_models/dalle3.py
swarm_models/embeddings_base.py
swarm_models/fuyu.py
swarm_models/gemini.py
swarm_models/gpt4_vision_api.py
swarm_models/huggingface.py
swarm_models/huggingface_pipeline.py
swarm_models/idefics.py
swarm_models/kosmos_two.py
swarm_models/layoutlm_document_qa.py
swarm_models/lite_llm_model.py
swarm_models/llama3_hosted.py
swarm_models/llama_function_caller.py
swarm_models/llava.py
swarm_models/model_router.py
swarm_models/model_types.py
swarm_models/moondream_mm.py
swarm_models/nougat.py
swarm_models/ollama_model.py
swarm_models/open_dalle.py
swarm_models/open_router.py
swarm_models/openai_embeddings.py
swarm_models/openai_function_caller.py
swarm_models/openai_tts.py
swarm_models/palm.py
swarm_models/popular_llms.py
swarm_models/qwen.py
swarm_models/sam.py
swarm_models/sam_two.py
swarm_models/sampling_params.py
swarm_models/ssd_1b.py
swarm_models/tiktoken_wrapper.py
swarm_models/together_llm.py
swarm_models/utils/__init__.py
swarm_models/utils/download_img_from_url.py
swarm_models/vilt.py
swarm_models/vip_llava.py
swarm_models/zeroscope.py
swarm_models-0.3.1.dist-info/LICENSE
swarm_models-0.3.1.dist-info/METADATA
swarm_models-0.3.1.dist-info/WHEEL
swarm_models-0.3.1.dist-info/RECORD
