Metadata-Version: 2.1
Name: swarm-models
Version: 0.3.1
Summary: Swarm Models - TGSC
Home-page: https://github.com/The-Swarm-Corporation/swarm-models
License: MIT
Keywords: artificial intelligence,deep learning,optimizers,Prompt Engineering,natural language processing,machine learning,pytorch,transformers
Author: Kye Gomez
Author-email: kye@apac.ai
Requires-Python: >=3.10,<4.0
Classifier: Development Status :: 4 - Beta
Classifier: Intended Audience :: Developers
Classifier: License :: OSI Approved :: MIT License
Classifier: Programming Language :: Python :: 3
Classifier: Programming Language :: Python :: 3.10
Classifier: Programming Language :: Python :: 3.11
Classifier: Programming Language :: Python :: 3.12
Classifier: Programming Language :: Python :: 3.9
Classifier: Topic :: Scientific/Engineering :: Artificial Intelligence
Requires-Dist: Pillow
Requires-Dist: langchain-community (==0.0.29)
Requires-Dist: litellm
Requires-Dist: loguru
Requires-Dist: ollama
Requires-Dist: pydantic
Requires-Dist: python-dotenv
Requires-Dist: termcolor
Requires-Dist: tiktoken
Requires-Dist: transformers
Project-URL: Documentation, https://github.com/The-Swarm-Corporation/swarm-models
Project-URL: Repository, https://github.com/The-Swarm-Corporation/swarm-models
